examples/__init__.py
examples/demo.py
examples/gigs.py
examples/kazeeki.py
examples/simple1.py
examples/simple2.py
examples/split.py
examples/usage.ipynb
examples/usage.py
examples/wired.py
riko/__init__.py
riko/autorss.py
riko/cast.py
riko/collections.py
riko/currencies.py
riko/dates.py
riko/dotdict.py
riko/locations.py
riko/parsers.py
riko/utils.py
riko/bado/__init__.py
riko/bado/io.py
riko/bado/itertools.py
riko/bado/microdom.py
riko/bado/mock.py
riko/bado/requests.py
riko/bado/sux.py
riko/bado/util.py
riko/data/.DS_Store
riko/data/Politik.xml
riko/data/TheEdTechie.xml
riko/data/Topthemen.xml
riko/data/autoblog.xml
riko/data/bbc.html
riko/data/bbci.co.uk.xml
riko/data/caltrain.html
riko/data/capnorth.xml
riko/data/cnn.html
riko/data/countries.csv
riko/data/currencies.csv
riko/data/currencies.json
riko/data/delicious.xml
riko/data/elance.json
riko/data/election_results.json
riko/data/feed.xml
riko/data/fourtitude.xml
riko/data/freelancer.json
riko/data/gawker.xml
riko/data/gigs.json
riko/data/greenhughes.xml
riko/data/guru.json
riko/data/health.xml
riko/data/lorem.txt
riko/data/odesk.json
riko/data/ouseful.xml
riko/data/ouseful_feedburner.xml
riko/data/places.xml
riko/data/podcast.xml
riko/data/psychemedia_delicious.xml
riko/data/psychemedia_slideshare.xml
riko/data/quote.json
riko/data/schools.xml
riko/data/sciencedaily.html
riko/data/scotland.xml
riko/data/spreadsheet.csv
riko/data/status.csv
riko/data/topstories.xml
riko/data/users.jyu.fi.html
riko/data/yodel.xml
riko/data/yql.xml
riko/modules/__init__.py
riko/modules/count.py
riko/modules/csv.py
riko/modules/currencyformat.py
riko/modules/dateformat.py
riko/modules/exchangerate.py
riko/modules/feedautodiscovery.py
riko/modules/fetch.py
riko/modules/fetchdata.py
riko/modules/fetchpage.py
riko/modules/fetchsitefeed.py
riko/modules/fetchtext.py
riko/modules/filter.py
riko/modules/geolocate.py
riko/modules/hash.py
riko/modules/input.py
riko/modules/itembuilder.py
riko/modules/join.py
riko/modules/refind.py
riko-0.67.0.dist-info/LICENSE
riko-0.67.0.dist-info/METADATA
riko-0.67.0.dist-info/WHEEL
riko-0.67.0.dist-info/top_level.txt
riko-0.67.0.dist-info/RECORD
