Metadata-Version: 2.1
Name: riko
Version: 0.67.0
Summary: A stream processing engine modeled after Yahoo! Pipes.
Home-page: https://github.com/nerevu/riko
Author: Reuben Cummings
Author-email: reubano@gmail.com
License: MIT
Download-URL: https://github.com/nerevu/riko/archive/v0.67.0.tar.gz
Keywords: riko,A,stream,processing,engine,modeled,after,Yahoo!,Pipes.
Platform: MacOS X
Platform: Windows
Platform: Linux
Classifier: License :: OSI Approved :: MIT License
Classifier: Development Status :: 4 - Beta
Classifier: Natural Language :: English
Classifier: Programming Language :: Python
Classifier: Programming Language :: Python :: 3
Classifier: Programming Language :: Python :: 3 :: Only
Classifier: Programming Language :: Python :: 3.7
Classifier: Programming Language :: Python :: 3.8
Classifier: Programming Language :: Python :: 3.9
Classifier: Programming Language :: Python :: Implementation :: CPython
Classifier: Programming Language :: Python :: Implementation :: PyPy
Classifier: Environment :: Console
Classifier: Topic :: Software Development :: Libraries :: Python Modules
Classifier: Intended Audience :: Developers
Classifier: Operating System :: POSIX :: Linux
Classifier: Operating System :: MacOS :: MacOS X
Classifier: Operating System :: Microsoft :: Windows
License-File: LICENSE
Requires-Dist: Babel (<3.0.0,>=2.8.0)
Requires-Dist: chardet (<4.0.0,>=3.0.4)
Requires-Dist: feedparser (<7.0.0,>=5.2.1)
Requires-Dist: meza (<1.0.0,>=0.42.5)
Requires-Dist: Mezmorize (<1.0.0,>=0.27.0)
Requires-Dist: python-dateutil (<3.0.0,>=2.8.1)
Requires-Dist: pygogo (<2.0.0,>=0.12.0)
Requires-Dist: requests (<3.0.0,>=2.22.0)
Requires-Dist: html5lib (<2.0.0,>=1.0.1)
Requires-Dist: pytz (>=2019.3)
Provides-Extra: async
Requires-Dist: treq (<22.0.0,>=18.6.0) ; extra == 'async'
Requires-Dist: Twisted (<22.0.0,>=19.10.0) ; extra == 'async'
Provides-Extra: develop
Requires-Dist: pip (>20.0) ; extra == 'develop'
Requires-Dist: wheel (>=0.29.0) ; extra == 'develop'
Requires-Dist: black (<22.0,>=19.3b0) ; extra == 'develop'
Requires-Dist: coverage (<6.0.0,>=4.3.4) ; extra == 'develop'
Requires-Dist: flake8 (<5.0.0,>=3.7.9) ; extra == 'develop'
Requires-Dist: flake8-black (<0.3.0,>=0.1.1) ; extra == 'develop'
Requires-Dist: nose (<2.0.0,>=1.3.7) ; extra == 'develop'
Requires-Dist: manage.py (<0.3.0,>=0.2.10) ; extra == 'develop'
Requires-Dist: pkutils (<4.0.0,>=3.0.0) ; extra == 'develop'
Requires-Dist: pylint (<3.0.0,>=2.5.0) ; extra == 'develop'
Requires-Dist: responses (<0.15.0,>=0.9.0) ; extra == 'develop'
Requires-Dist: scripttest (<2.0,>=1.3) ; extra == 'develop'
Requires-Dist: setuptools (>=42.0.2) ; extra == 'develop'
Requires-Dist: tox (<4.0.0,>=3.14.3) ; extra == 'develop'
Requires-Dist: twine (<4.0.0,>=3.2.0) ; extra == 'develop'
Provides-Extra: xml
Requires-Dist: lxml (<5.0.0,>=4.5.0) ; extra == 'xml'
Requires-Dist: speedparser3 (~=0.3.1) ; extra == 'xml'
